fb_normalize_and_hash/__init__.py
fb_normalize_and_hash/fb_normalize_and_hash.py
fb_normalize_and_hash/fb_normalize_and_hash_constants.py
fb_normalize_and_hash-0.1.dist-info/METADATA
fb_normalize_and_hash-0.1.dist-info/WHEEL
fb_normalize_and_hash-0.1.dist-info/top_level.txt
fb_normalize_and_hash-0.1.dist-info/RECORD
