Metadata-Version: 2.1
Name: fb-normalize-and-hash
Version: 0.1
Summary: Python library to normalize and hash signals data
Home-page: UNKNOWN
Author: William Li
Author-email: liwilliam@fb.com
License: UNKNOWN
Platform: UNKNOWN
Requires-Python: >=3
